{
  "$meta": {
    "product": "七星體育",
    "version": "0.2.0-draft",
    "generatedAt": "2026-07-07",
    "levels": {
      "error": "違反必須修正",
      "warning": "需設計裁決或建議修正"
    }
  },
  "global": [
    {
      "id": "G-001",
      "level": "error",
      "rule": "元件內顏色一律引用 semantic 層變數 var(--),禁止直接寫 hex 或 rgba",
      "rationale": "現況投注 CTA 漸層(rgba(41,115,184,0.9)→#2B73B5)整組寫死,主要行動按鈕反而是全檔案唯一沒有變數保護的顏色"
    },
    {
      "id": "G-002",
      "level": "error",
      "rule": "同色值不同語意必須獨立命名。status/error、odds/up、result/win 三者即使同為 #FF6954,永遠是三個獨立 token,合併只允許發生在 alias 層",
      "rationale": "現況 #FF6954 同時被 status/error、辅助色/error、input/error 三個無 alias 關係的變數引用,改任何一個都可能連動賠率與盈虧顯示"
    },
    {
      "id": "G-003",
      "level": "error",
      "rule": "禁止語意反轉命名。正向狀態(贏)不得綁定名為 error 的變數,負向狀態(輸)不得綁定名為 success 的變數",
      "rationale": "現況「贏」的金額綁在 辅助色/error,「輸」綁在 辅助色/success,任何新人接手必定誤用"
    },
    {
      "id": "G-004",
      "level": "error",
      "rule": "變數命名語言統一使用英文,層級分隔用正斜線。禁止中英兩套平行變數並存",
      "rationale": "現況 status/error 與 辅助色/error 為同值雙包,分別被不同元件引用,已形成壞重複"
    },
    {
      "id": "G-005",
      "level": "error",
      "rule": "賠率、盤口、比分、盈虧等即時資料色一律掛 live-data tag,規則批次管理,禁止與一般 UI 狀態色共用規則",
      "rationale": "即時資料的紅綠邏輯(紅漲綠跌、紅贏綠輸)與系統回饋的紅綠邏輯(紅錯綠對)方向相反,共用規則必出事"
    },
    {
      "id": "G-006",
      "level": "error",
      "rule": "中文、英文介面文案與一般標籤文字使用 PingFang HK;所有數字類文字(賠率、比分、金額、限額、時間、百分比、計數、統計)使用 DIN Alternate Bold",
      "rationale": "設計 owner 2026-07-07 確認:文字統一 PingFang HK,數字統一 DIN。此規則升級為 plugin hard rule。"
    },
    {
      "id": "G-007",
      "level": "warning",
      "rule": "字級尺度限定 10 / 12 / 14 / 16。現況存在 15px(可贏標籤)一處,建議併入尺度",
      "rationale": "孤立字級會讓之後的響應式與國際化調整多一個特例"
    },
    {
      "id": "G-008",
      "level": "error",
      "rule": "高頻重複的畫面單元(賽事卡、注單卡)必須做成 component,禁止以散裝 frame 複製貼上維護多狀態",
      "rationale": "現況賽事卡有 8 種狀態(未開賽~點球大戰)全是普通 frame,內部圖層全為 Frame 159788xxxx 佔位名,且整卡零變數引用"
    },
    {
      "id": "G-009",
      "level": "error",
      "rule": "同一色值禁止建立多個無 alias 關係的變數。新增變數前必須先查現有變數表",
      "rationale": "#45A6FF 現況同時存在 brand/primary 與 main/b80 兩個變數;紅綠也各有 status/* 與 辅助色/* 雙包,重複已成系統性慣性"
    },
    {
      "id": "G-010",
      "level": "error",
      "rule": "禁止 PingFang HK / PingFang SC 混用。所有非數字文案統一使用 PingFang HK",
      "rationale": "設計 owner 已指定 PingFang HK 為文字標準。現況同一張賽事卡內主/客/和標籤用 PingFang SC,其餘用 PingFang HK,需修正。"
    },
    {
      "id": "G-011",
      "level": "warning",
      "rule": "賠率數字字級統一(OddsValue 元件 14px vs 賽事卡 13px,擇一),行高使用整數",
      "rationale": "同一種資料(賠率)在不同容器字級不同,且存在 16.5px 非整數行高"
    },
    {
      "id": "G-012",
      "level": "warning",
      "rule": "同一個文字圖層若同時包含文案與數字,需確認是否可拆成文案層與數字層;若不拆,文字範圍需保留 PingFang HK,數字範圍需套 DIN Alternate Bold",
      "rationale": "體育產品常出現「可赢 238,114.00」「第 90 分鐘」這類混合字串。拆層或 range font 才能讓工程與 plugin 準確對應字體。"
    }
  ],
  "naming": [
    {
      "id": "N-001",
      "level": "error",
      "rule": "元件命名統一英文 PascalCase,可加斜線分類前綴(如 Icon/Pin)。同類元件禁止多種格式",
      "rationale": "現況 icon 一類就有 Icon/Pin、icon 16px、Icon_12px、icon / 搜索 四種格式並存"
    },
    {
      "id": "N-002",
      "level": "error",
      "rule": "Variant 屬性名限定 State / Type / Size / Trend 等語意名,禁止 Property 1 佔位名",
      "rationale": "現況至少 9 種屬性名並存:State、Property 1、play、赛况、数值、已讀、分类、Tab State、Search State。Property 1 佔位名即為揪錯貓既有偵測項"
    },
    {
      "id": "N-003",
      "level": "error",
      "rule": "同一檔案內文案與命名的繁簡體必須統一(產品文案依產品慣例用簡體,圖層命名建議英文迴避此問題)",
      "rationale": "現況同一個 Navigation Bar 元件集內 State=標題＋返回(繁)與 State=筛选(簡)混用"
    },
    {
      "id": "N-004",
      "level": "error",
      "rule": "Variant 值大小寫統一(Focus 或 focus 擇一,建議小寫)",
      "rationale": "現況兩個 tab_btn 元件集分別使用 Focus 與 focus"
    },
    {
      "id": "N-005",
      "level": "error",
      "rule": "元件集名稱在同一檔案內必須唯一",
      "rationale": "現況 tab_btn 有兩組(7909:36356、7909:40601)、amount 有兩組(7870:264600、7870:264631),引用時無法辨識"
    },
    {
      "id": "N-006",
      "level": "warning",
      "rule": "元件集的語意分類必須正確:國旗集只放國旗,俱樂部隊徽另立 ClubBadge 集",
      "rationale": "現況「国旗」集內混入兵工厂、曼城、巴黎圣日尔曼、布蘭特福德等隊徽,檢索必然失敗"
    }
  ],
  "component": [
    {
      "id": "C-001",
      "level": "error",
      "component": "SlideBetButton",
      "rule": "四個狀態(Default/Dragging/Success/Disabled)圓角必須一致為 pill(500px)",
      "rationale": "現況 Disabled 態圓角 40px,其餘 500px"
    },
    {
      "id": "C-002",
      "level": "error",
      "component": "BetAmountInput",
      "rule": "邊框:預設態綁 color/input/border,錯誤態綁 color/input/border-error,禁止直接引用 text 系 token",
      "rationale": "現況 input/stroke 與 text/secondary 同值 #61819E,必須維持獨立命名,改文字色不得連動輸入框"
    },
    {
      "id": "C-003",
      "level": "error",
      "component": "OddsValue",
      "rule": "Trend=Up 綁 color/odds/up、Down 綁 color/odds/down、None 綁 color/odds/none,禁止綁 status 系 token",
      "rationale": "現況 Up 綁 status/error、Down 綁 status/success,語意錯置"
    },
    {
      "id": "C-004",
      "level": "error",
      "component": "已结算注单(結算狀態系列)",
      "rule": "贏綁 color/result/win、輸綁 color/result/loss、平綁 color/result/draw,禁止綁 status 或 辅助色 系 token",
      "rationale": "現況贏綁 辅助色/error、輸綁 辅助色/success,語意反轉"
    },
    {
      "id": "C-005",
      "level": "warning",
      "component": "OddsValue",
      "rule": "Trend=locked 的鎖定 icon 色需定義 token(color/odds/locked),現況為 SVG 內嵌色未驗證",
      "rationale": "未綁變數的 icon 色在換膚或深淺色模式時會漏改"
    },
    {
      "id": "C-006",
      "level": "warning",
      "component": "互動狀態完整性",
      "rule": "可互動元件至少定義 default / focus(selected) / disabled 三態;現況多數元件僅 default / focus 兩態",
      "rationale": "缺 disabled 態的元件上線後遇到停盤、封盤場景會臨時湊色"
    },
    {
      "id": "C-007",
      "level": "error",
      "component": "賽事卡(赛事状态系列)",
      "rule": "卡底綁 color/surface/card、時間與賠率綁 odds 族、選項底綁 color/surface/option、標籤綁 color/text/option-label;全卡現況零變數,須全面綁定",
      "rationale": "賽事卡是首頁最高頻元素,現況 #212E39、#45A6FF、#7497B7、#506D87、rgba(255,255,255,.03) 全部寫死"
    }
  ]
}
